django_cached_counts/__init__.py
django_cached_counts-0.2.1.dist-info/METADATA
django_cached_counts-0.2.1.dist-info/WHEEL
django_cached_counts-0.2.1.dist-info/RECORD
