Metadata-Version: 2.1
Name: django_cached_counts
Version: 0.2.1
Summary: Caching count() in django models
License: MIT
Author: ph
Author-email: robotnaoborot@gmail.com
Requires-Python: >=3.8,<4.0
Classifier: License :: OSI Approved :: MIT License
Classifier: Programming Language :: Python :: 3
Classifier: Programming Language :: Python :: 3.8
Classifier: Programming Language :: Python :: 3.9
Classifier: Programming Language :: Python :: 3.10
Classifier: Programming Language :: Python :: 3.11
Classifier: Programming Language :: Python :: 3.12
Requires-Dist: django (>=3.2,<4.0)
